finecode_builtin_handlers/__init__.py
finecode_builtin_handlers/dependency_config_utils.py
finecode_builtin_handlers/dump_config.py
finecode_builtin_handlers/dump_config_save.py
finecode_builtin_handlers/prepare_envs_install_deps.py
finecode_builtin_handlers/prepare_envs_read_configs.py
finecode_builtin_handlers/prepare_runners_install_runner_and_presets.py
finecode_builtin_handlers/prepare_runners_read_configs.py
finecode_builtin_handlers-0.1.0.dist-info/METADATA
finecode_builtin_handlers-0.1.0.dist-info/WHEEL
finecode_builtin_handlers-0.1.0.dist-info/top_level.txt
finecode_builtin_handlers-0.1.0.dist-info/RECORD
