Metadata-Version: 2.4
Name: finecode_builtin_handlers
Version: 0.1.0
Summary: FineCode built-in handlers
Author-email: Vladyslav Hnatiuk <aders1234@gmail.com>
Requires-Python: <3.14,>=3.11
Requires-Dist: finecode_extension_api==0.3.*
Requires-Dist: tomlkit==0.11.*
